spawn_user_agent/__init__.py
spawn_user_agent/__main__.py
spawn_user_agent/user_agent.py
spawn_user_agent-0.0.4.dist-info/licenses/LICENSE.md
spawn_user_agent-0.0.4.dist-info/WHEEL
spawn_user_agent-0.0.4.dist-info/METADATA
spawn_user_agent-0.0.4.dist-info/RECORD
