Metadata-Version: 2.4
Name: spawn-user-agent
Version: 0.0.4
Summary: Super simple user agent generator
Keywords: user-agent
Author: Fastily
Author-email: Fastily <fastily@users.noreply.github.com>
License-Expression: GPL-3.0-or-later
License-File: LICENSE.md
Classifier: Natural Language :: English
Classifier: Programming Language :: Python :: 3
Classifier: Programming Language :: Python :: 3.9
Classifier: License :: OSI Approved :: GNU General Public License v3 (GPLv3)
Classifier: Operating System :: OS Independent
Requires-Python: >=3.9
Project-URL: Bug Tracker, https://github.com/fastily/spawn-user-agent/issues
Project-URL: Homepage, https://github.com/fastily/spawn-user-agent
